lunar_tools/__init__.py
lunar_tools/audio.py
lunar_tools/cam.py
lunar_tools/config.py
lunar_tools/control_input.py
lunar_tools/display_window.py
lunar_tools/fontrender.py
lunar_tools/fps_tracker.py
lunar_tools/health_reporting.py
lunar_tools/image_gen.py
lunar_tools/llm.py
lunar_tools/logprint.py
lunar_tools/midi.py
lunar_tools/movie.py
lunar_tools/realtime_voice.py
lunar_tools/torch_utils.py
lunar_tools/utils.py
lunar_tools/comms/__init__.py
lunar_tools/comms/osc.py
lunar_tools/comms/utils.py
lunar_tools/comms/webrtc.py
lunar_tools/comms/webrtc_codec.py
lunar_tools/comms/webrtc_signaling.py
lunar_tools/comms/zmq.py
lunar_tools/midi_configs/akai_lpd8.yml
lunar_tools/midi_configs/akai_midimix.yml
lunar_tools-0.5.dist-info/LICENSE
lunar_tools-0.5.dist-info/METADATA
lunar_tools-0.5.dist-info/WHEEL
lunar_tools-0.5.dist-info/top_level.txt
lunar_tools-0.5.dist-info/RECORD
