Metadata-Version: 2.1
Name: lunar-tools
Version: 0.5
Summary: Lunar Ring auxiliary tools and modules for programming interactive exhibitions
Home-page: https://github.com/lunarring/lunar_tools
Author-email: Lunar Ring <info@lunarring.ai>
License: BSD 3-Clause License
Project-URL: Homepage, https://github.com/lunarring/lunar_tools
Project-URL: Repository, https://github.com/lunarring/lunar_tools
Project-URL: Issues, https://github.com/lunarring/lunar_tools/issues
Keywords: multimedia,interactive,exhibitions,audio,video,webrtc,midi
Classifier: Development Status :: 3 - Alpha
Classifier: Intended Audience :: Developers
Classifier: License :: OSI Approved :: MIT License
Classifier: Programming Language :: Python :: 3
Classifier: Programming Language :: Python :: 3.10
Classifier: Programming Language :: Python :: 3.11
Classifier: Programming Language :: Python :: 3.12
Classifier: Topic :: Multimedia
Classifier: Topic :: Multimedia :: Graphics
Classifier: Topic :: Multimedia :: Sound/Audio
Classifier: Topic :: Multimedia :: Video
Requires-Python: >=3.10
License-File: LICENSE
Requires-Dist: fal-client
Requires-Dist: elevenlabs
Requires-Dist: ffmpeg
Requires-Dist: ffmpeg-python
Requires-Dist: matplotlib
Requires-Dist: moviepy
Requires-Dist: numpy
Requires-Dist: openai
Requires-Dist: opencv-python
Requires-Dist: Pillow
Requires-Dist: pygame
Requires-Dist: pynput
Requires-Dist: pydub
Requires-Dist: python-osc
Requires-Dist: PyOpenGL
Requires-Dist: PySDL2
Requires-Dist: PyYAML
Requires-Dist: pysdl2-dll
Requires-Dist: replicate
Requires-Dist: requests
Requires-Dist: rich
Requires-Dist: setuptools
Requires-Dist: sounddevice
Requires-Dist: tqdm
Requires-Dist: pyusb
Requires-Dist: pyzmq
Requires-Dist: aiortc (>=1.7.0)
Requires-Dist: aiohttp (>=3.8.0)
Provides-Extra: dev
Requires-Dist: pytest ; extra == 'dev'
Requires-Dist: pipreqs ; extra == 'dev'
Provides-Extra: torch
Requires-Dist: torch (>=2.0.0) ; extra == 'torch'
